LICENSE
MANIFEST.in
README.md
setup.cfg
setup.py
rancher_gen/__init__.py
rancher_gen/cli.py
rancher_gen/compat.py
rancher_gen/exception.py
rancher_gen/handler.py
rancher_gen/rancher.py
rancher_gen.egg-info/PKG-INFO
rancher_gen.egg-info/SOURCES.txt
rancher_gen.egg-info/dependency_links.txt
rancher_gen.egg-info/entry_points.txt
rancher_gen.egg-info/requires.txt
rancher_gen.egg-info/top_level.txt
tests/fixtures/__init__.py
tests/fixtures/rancher_fixtures.py